applepylog/__init__.py
applepylog/logger.py
applepylog-0.1.5.dist-info/METADATA
applepylog-0.1.5.dist-info/WHEEL
applepylog-0.1.5.dist-info/top_level.txt
applepylog-0.1.5.dist-info/RECORD
