Metadata-Version: 2.2
Name: applepylog
Version: 0.1.5
Summary: A simple logger for basic projects
Home-page: https://github.com/ChrisYeomans/ApplePyLog
Author: Chris Yeomans
Author-email: chris.shorelinetech@gmail.com
Classifier: Programming Language :: Python :: 3
Classifier: License :: OSI Approved :: MIT License
Classifier: Operating System :: OS Independent
Dynamic: author
Dynamic: author-email
Dynamic: classifier
Dynamic: description
Dynamic: description-content-type
Dynamic: home-page
Dynamic: summary
